{
	"translations": {
		"de": {
			"__variableprofile__": "OpenSprinkler.YesNo",
			"yes": "Ja",
			"no": "Nein",

			"__variableprofile__": "OpenSprinkler.ControllerState",
			"enabled": "aktiviert",
			"disabled": "deaktiviert",

			"__variableprofile__": "OpenSprinkler.SensorState",
			"triggered": "ausgelöst",

			"__variableprofile__": "OpenSprinkler.StationState",
			"disabled": "deaktiviert",
			"ready": "bereit",
			"queued": "anstehend",
			"watering": "bewässert",
			"closed": "geschlossen",
			"opened": "geöffnet",

			"__variableprofile__": "OpenSprinkler.ProgramState",
			"disabled": "deaktiviert",
			"ready": "bereit",
			"queued": "anstehend",
			"running": "läuft",

			"__variableprofile__": "OpenSprinkler.ProgramStart",
			"with weather adjustment": "mit Wetteranpassung",
			"without weather adjustment": "ohne Wetteranpassung",

			"__variableprofile__": "OpenSprinkler.StopAllStations",
			"Execute": "Ausführen",

			"__variableprofile__": "OpenSprinkler.RainDelayAction",
			"Set": "Setzen",
			"Clear": "Löschen",

			"__variableprofile__": "OpenSprinkler.PauseQueueAction_<ObjectID>",
			"Set": "Setzen",
			"Clear": "Löschen",

			"__variableprofile__": "OpenSprinkler.StationStartManually_<ObjectID>",
			"Start": "Starten",
			"Stop": "Stoppen",

			"__variableprofile__": "OpenSprinkler.WeatherStatus",
			"Ok": "OK",
			"Request not received": "Anfrage nicht erhalten",
			"Cannot connect to weather server": "Verbindung zum Wetterserver nicht möglich",
			"Request time out": "Zeitüberschreitung bei der Anfrage",
			"Received empty return": "Leere Rückgabe erhalten",
			"Problem with the weather information": "Problem mit den Wetterinformationen",
			"No 24 hour period available": "Kein 24-Stunden-Zeitraum verfügbar",
			"Missing field in weather data": "Feld in Wetterdaten fehlt",
			"API error": "API-Fehler",
			"Location not resolved": "Standort nicht aufgelöst",
			"Error resolvind location": "Fehler beim Auflösen des Standorts",
			"Location not found": "Standort nicht gefunden",
			"Location format error": "Fehler im Standortformat",
			"PWS error": "PWS-Fehler",
			"Invalid PWS ID": "Ungültige PWS-ID",
			"Invalid PWS API key": "Ungültiger PWS-API-Schlüssel",
			"PWS authentification error": "PWS-Authentifizierungsfehler",
			"PWS data missing": "PWS-Daten fehlen",
			"PWS mot provided": "PWS-Mot nicht bereitgestellt",
			"Error in adjustment or watering restrictions": "Fehler bei Anpassungs- oder Bewässerungsbeschränkungen",
			"Adjustment incompatible to weather service": "Anpassung nicht kompatibel mit Wetterdienst",
			"Invalid adjustment method": "Ungültige Anpassungsmethode",
			"Error in adjustment options": "Fehler bei Anpassungsoptionen",
			"Malformed adjustment option": "Fehlerhafte Anpassungsoption",
			"Adjustment option missing": "Anpassungsoption fehlt",
			"Unexpected error": "Unerwarteter Fehler",

			"__variableprofile__": "OpenSprinkler.RebootCause",
			"None": "Keine",
			"Factory reset": "Auf Werkseinstellungen zurückgesetzt",
			"Triggered by buttons": "Durch Schaltflächen ausgelöst",
			"Reset to AP mode": "Zurücksetzen in AP-Modus",
			"Timer triggered reboot": "Neustart durch Timer ausgelöst",
			"API triggered reboot": "Neustart durch API ausgelöst",
			"Switch from AP to client mode": "Wechsel von AP- zu Client-Modus",
			"Firmware update": "Firmware-Aktualisierung",
			"Weather call failed for more than 24 hours": "Wetteranruf seit mehr als 24 Stunden fehlgeschlagen",
			"Network failed for too many times": "Netzwerk zu oft ausgefallen",
			"Reboot due to first-time NTP sync": "Neustart aufgrund erstmaliger NTP-Synchronisierung",
			"Triggered by program": "Durch Programm ausgelöst",
			"Power on": "Einschalten",

			"__options__": "SensorType",
			"Rain sensor": "Regensensor",
			"Flow sensor": "Durchflusssensor",
			"Soil sensor": "Bodenfeuchtesensor",
			"Program switch": "Programmschalter",
			"Unknown sensor type": "Unbekannter Sensortyp",

			"__options__": "SensorOption",
			"normally open": "normalerweise offen",
			"normally closed": "normalerweise geschlossen",
			"Unknown sensor option": "Unbekannter Sensor-Option",

			"__options__": "WeatherMethod",
			"Manual operation": "Handbetrieb",
			"Zimmermann": "Zimmermann",
			"Auto rain delay": "automatische Regenverzögerung",
			"ETo": "ETo",
			"Monthly": "Monatlich",
			"Unknown weather method": "Unbekannte Wetter-Methode",

			"__options__": "ProgramDayRestriction",
			"none": "keine",
			"odd": "ungerade",
			"even": "gerade",
			"Unknown program day restriction": "Unbekannte Programm-Tageseinschränkung",

			"__options__": "ProgramScheduleType",
			"weekday": "Wochentag",
			"interval": "Intervall",
			"Unknown program schedule type": "Unbekannte Programmart-Typ",

			"__options__": "ProgramStarttimeType",
			"repeating": "wiederholt",
			"fixed": "fest",
			"Unknown program starttime type": "Unbekannte Programm-Startzeiten-Typ",

			"__options__": "LogGroupBy",
			"None": "Keine",
			"Date": "Datum",
			"Station ID": "Bewässerungskreis-ID",
			"Station name": "Bewässerungskreis-Name",

			"__options__": "LogDays",
			"today only": "nur heute",

			"__status__": "",
			"Instance is inactive (unauthorized)": "Instanz ist inaktiv (Authorisierung fehlerhaft)",
			"Instance is inactive (forbidden)": "Instanz ist inaktiv (fehlende Berechtigung)",
			"Instance is inactive (server error)": "Instanz ist inaktiv (Serverfehler)",
			"Instance is inactive (http error)": "Instanz ist inaktiv (HTTP-Fehler)",
			"Instance is inactive (invalid data)": "Instanz ist inaktiv (ungültige Daten)",

			"__end__": ""
		}
	}
}
